setup.py
RE_2/__init__.py
Resident_Evil_stuff.egg-info/PKG-INFO
Resident_Evil_stuff.egg-info/SOURCES.txt
Resident_Evil_stuff.egg-info/dependency_links.txt
Resident_Evil_stuff.egg-info/requires.txt
Resident_Evil_stuff.egg-info/top_level.txt
bin/dist/RE_2.exe
bin/dist/config.exe
bin/dist/stats.exe
bin/dist/zombie_combat.exe
bin/dist/RE_2.exe
bin/dist/config.exe
bin/dist/stats.exe
bin/dist/zombie_combat.exe