Metadata-Version: 1.1
Name: Resident-Evil-stuff
Version: 0.1
Summary: A Resident Evil Game.
Home-page: https://pypi.python.org/pypi?%3Aaction=pkg_edit&name=RE_2
Author: Barbara Rodriguez
Author-email: barbarajrodriguez542@gmail.com
License: UNKNOWN
Download-URL: https://pypi.python.org/pypi?%3Aaction=pkg_edit&name=RE_2
Platform: UNKNOWN
